mdgrad/__init__.py
mdgrad/optim.py
mdgrad/tensor.py
mdgrad/nn/__init__.py
mdgrad/nn/activations.py
mdgrad/nn/layers.py
mdgrad/nn/losses.py
mdgrad/nn/utils.py
mdgrad-0.3.dist-info/LICENSE
mdgrad-0.3.dist-info/METADATA
mdgrad-0.3.dist-info/WHEEL
mdgrad-0.3.dist-info/top_level.txt
mdgrad-0.3.dist-info/RECORD
