Metadata-Version: 2.1
Name: mdgrad
Version: 0.3
Summary: Tensor-based autdiff engine and neural network API
Author: Jordan Madden
Author-email: <jordanmadden285@gmail.com>
Keywords: python,tensors,neural networks,automatic differentiation
Classifier: Intended Audience :: Developers
Classifier: Programming Language :: Python :: 3
Classifier: Operating System :: Unix
Classifier: Operating System :: MacOS :: MacOS X
Classifier: Operating System :: Microsoft :: Windows
Requires-Python: >=3.8
License-File: LICENSE
Requires-Dist: numpy
